boostedprob/__init__.py
boostedprob-0.1.1.dist-info/licenses/LICENSE
boostedprob-0.1.1.dist-info/METADATA
boostedprob-0.1.1.dist-info/WHEEL
boostedprob-0.1.1.dist-info/top_level.txt
boostedprob-0.1.1.dist-info/RECORD
