Metadata-Version: 2.4
Name: boostedprob
Version: 0.1.1
Summary: Utilities to identify dominant tokens and compute boosted model probabilities for Quality Estimation.
Author-email: Tu Anh Dinh <dinhtuanh23@gmail.com>
License: MIT
Project-URL: Homepage, https://github.com/TuAnh23/boostedprob
Project-URL: Repository, https://github.com/TuAnh23/boostedprob
Requires-Python: >=3.9
License-File: LICENSE
Requires-Dist: torch>=2.0.1
Dynamic: license-file
